discolinks/__init__.py
discolinks/__main__.py
discolinks/__version__.py
discolinks/analyzer.py
discolinks/cli.py
discolinks/core.py
discolinks/excluder.py
discolinks/export.py
discolinks/html.py
discolinks/link_extractor.py
discolinks/monitor.py
discolinks/outcome.py
discolinks/py.typed
discolinks/requester.py
discolinks/text.py
discolinks/url_store.py
discolinks/worker.py
discolinks-0.3.0.dist-info/LICENSE
discolinks-0.3.0.dist-info/METADATA
discolinks-0.3.0.dist-info/WHEEL
discolinks-0.3.0.dist-info/entry_points.txt
discolinks-0.3.0.dist-info/RECORD
