Metadata-Version: 2.1
Name: discolinks
Version: 0.3.0
Summary: Command-line tool which checks a website for broken links.
License: MIT
Keywords: crawler,http,html,link,url,web
Author: Bertrand Bonnefoy-Claudet
Author-email: bertrand@bertrandbc.com
Requires-Python: >=3.9,<4.0
Classifier: License :: OSI Approved :: MIT License
Classifier: Programming Language :: Python :: 3
Classifier: Programming Language :: Python :: 3.9
Classifier: Programming Language :: Python :: 3.10
Classifier: Programming Language :: Python :: 3.11
Classifier: Programming Language :: Python :: 3.12
Classifier: Programming Language :: Python :: Implementation :: CPython
Classifier: Typing :: Typed
Requires-Dist: attrs (>=24.2.0,<25.0.0)
Requires-Dist: beautifulsoup4 (>=4.11.1,<5.0.0)
Requires-Dist: click (>=8.1.3,<9.0.0)
Requires-Dist: httpx (>=0.27.0,<0.28.0)
Requires-Dist: rich (>=13.3.1,<14.0.0)
